setup.py
piped.contrib.statsd.egg-info/PKG-INFO
piped.contrib.statsd.egg-info/SOURCES.txt
piped.contrib.statsd.egg-info/dependency_links.txt
piped.contrib.statsd.egg-info/requires.txt
piped.contrib.statsd.egg-info/top_level.txt
piped/plugins/statsd_plugin.py
piped_statsd/__init__.py
piped_statsd/client.py
piped_statsd/reporter.py