Metadata-Version: 1.1
Name: piped.contrib.statsd
Version: 0.7.0
Summary: StatsD-utilities for Piped.
Home-page: http://piped.io
Author: Piped Project Contributors
Author-email: piped@librelist.com
License: MIT
Platform: UNKNOWN
Classifier: Development Status :: 4 - Beta
Classifier: Environment :: Plugins
Classifier: Framework :: Twisted
Classifier: Operating System :: OS Independent
